randomgen-2.3.0.dist-info/RECORD
randomgen-2.3.0.dist-info/WHEEL
randomgen-2.3.0.dist-info/METADATA
randomgen-2.3.0.dist-info/licenses/LICENSE.md
randomgen/mt64.pyi
randomgen/xoroshiro128.pyi
randomgen/romu.cpython-314t-darwin.so
randomgen/_register.py
randomgen/philox.cpython-314t-darwin.so
randomgen/entropy.cpython-314t-darwin.so
randomgen/conftest.py
randomgen/chacha.cpython-314t-darwin.so
randomgen/wrapper.cpython-314t-darwin.so
randomgen/rdrand.pyi
randomgen/xoshiro256.cpython-314t-darwin.so
randomgen/squares.cpython-314t-darwin.so
randomgen/_version.py
randomgen/speck128.pyi
randomgen/_pickle.py
randomgen/_seed_sequence.cpython-314t-darwin.so
randomgen/hc128.cpython-314t-darwin.so
randomgen/threefry.pyi
randomgen/entropy.pyi
randomgen/xoroshiro128.cpython-314t-darwin.so
randomgen/xoshiro256.pyi
randomgen/pcg32.pyi
randomgen/pcg64.cpython-314t-darwin.so
randomgen/generator.pyi
randomgen/threefry.cpython-314t-darwin.so
randomgen/__init__.py
randomgen/lxm.pyi
randomgen/common.cpython-314t-darwin.so
randomgen/common.pyi
randomgen/lxm.cpython-314t-darwin.so
randomgen/wrapper.pyi
randomgen/chacha.pyi
randomgen/aes.pyi
randomgen/mt19937.pyi
randomgen/xoshiro512.pyi
randomgen/xoshiro512.cpython-314t-darwin.so
randomgen/dsfmt.cpython-314t-darwin.so
randomgen/philox.pyi
randomgen/broadcasting.cpython-314t-darwin.so
randomgen/xorshift1024.cpython-314t-darwin.so
randomgen/tyche.pyi
randomgen/blabla.cpython-314t-darwin.so
randomgen/pcg32.cpython-314t-darwin.so
randomgen/rdrand.cpython-314t-darwin.so
randomgen/efiix64.cpython-314t-darwin.so
randomgen/speck128.cpython-314t-darwin.so
randomgen/sfc.pyi
randomgen/sfmt.pyi
randomgen/sfc.cpython-314t-darwin.so
randomgen/romu.pyi
randomgen/typing.py
randomgen/dsfmt.pyi
randomgen/xorshift1024.pyi
randomgen/aes.cpython-314t-darwin.so
randomgen/pcg64.pyi
randomgen/mtrand.pyi
randomgen/efiix64.pyi
randomgen/seed_sequence.py
randomgen/mt19937.cpython-314t-darwin.so
randomgen/tyche.cpython-314t-darwin.so
randomgen/jsf.pyi
randomgen/mt64.cpython-314t-darwin.so
randomgen/sfmt.cpython-314t-darwin.so
