Metadata-Version: 2.4
Name: randomgen
Version: 2.3.0
Summary: Random generator supporting multiple PRNGs
Keywords: pseudo random numbers,PRNG,RNG,RandomState,random,random numbers,parallel random numbers,PCG,XorShift,dSFMT,MT19937,Random123,ThreeFry,Philox,ChaCha,AES,SPECK,RDRAND
Author-Email: Kevin Sheppard <kevin.k.sheppard@gmail.com>
Maintainer-Email: Kevin Sheppard <kevin.k.sheppard@gmail.com>
License-Expression: NCSA
License-File: LICENSE.md
Classifier: Development Status :: 5 - Production/Stable
Classifier: Environment :: Console
Classifier: Intended Audience :: End Users/Desktop
Classifier: Intended Audience :: Financial and Insurance Industry
Classifier: Intended Audience :: Information Technology
Classifier: Intended Audience :: Science/Research
Classifier: Operating System :: MacOS :: MacOS X
Classifier: Operating System :: Microsoft :: Windows
Classifier: Operating System :: POSIX :: Linux
Classifier: Operating System :: Unix
Classifier: Programming Language :: C
Classifier: Programming Language :: Cython
Classifier: Programming Language :: Python :: 3.8
Classifier: Programming Language :: Python :: 3.9
Classifier: Programming Language :: Python :: 3.10
Classifier: Programming Language :: Python :: 3.11
Classifier: Topic :: Adaptive Technologies
Classifier: Topic :: Artistic Software
Classifier: Topic :: Office/Business :: Financial
Classifier: Topic :: Scientific/Engineering
Classifier: Topic :: Security :: Cryptography
Project-URL: homepage, https://github.com/bashtage/randomgen
Project-URL: documentation, https://bashtage.github.io/randomgen/
Project-URL: repository, https://github.com/bashtage/randomgen
Project-URL: changelog, https://bashtage.github.io/randomgen/change-log.html
Requires-Python: >=3.8
Requires-Dist: numpy<3,>=1.22.3
Provides-Extra: test
Requires-Dist: pytest<9,>=8.4.1; extra == "test"
Requires-Dist: pytest-randomly; extra == "test"
Requires-Dist: pytest-xdist; extra == "test"
Requires-Dist: pytest-cov; extra == "test"
Requires-Dist: coverage[toml]; extra == "test"
Requires-Dist: meson; extra == "test"
Requires-Dist: ninja; extra == "test"
Provides-Extra: doc
Requires-Dist: setuptools>=61; extra == "doc"
Requires-Dist: wheel; extra == "doc"
Requires-Dist: setuptools_scm[toml]<9,>=8.0.3; extra == "doc"
Requires-Dist: oldest-supported-numpy; extra == "doc"
Requires-Dist: cython<4,>=3.0.13; extra == "doc"
Requires-Dist: numpy>=1.22; extra == "doc"
Requires-Dist: scipy>=1.5.0; extra == "doc"
Requires-Dist: ipython>=8.0.1; extra == "doc"
Requires-Dist: matplotlib>=3.0; extra == "doc"
Requires-Dist: patsy>=0.5.3; extra == "doc"
Requires-Dist: statsmodels>=0.13.5; extra == "doc"
Requires-Dist: jinja2; extra == "doc"
Requires-Dist: sphinx>=7; extra == "doc"
Requires-Dist: seaborn; extra == "doc"
Requires-Dist: numpydoc>=1.0.0; extra == "doc"
Requires-Dist: nbsphinx; extra == "doc"
Requires-Dist: sphinx-immaterial; extra == "doc"
Requires-Dist: jupyter; extra == "doc"
Requires-Dist: notebook; extra == "doc"
Requires-Dist: sphinx-autodoc-typehints; extra == "doc"
Requires-Dist: fonttools>=4.43.0; extra == "doc"
Requires-Dist: jupyterlab>=4.4.8; extra == "doc"
Requires-Dist: ipython>=7; extra == "doc"
Requires-Dist: sphinx_immaterial; extra == "doc"
Requires-Dist: nbconvert; extra == "doc"
Requires-Dist: pickleshare; extra == "doc"
Requires-Dist: pandas~=2.3.3; extra == "doc"
Provides-Extra: dev
Requires-Dist: setuptools_scm[toml]<10,>=9.2.0; extra == "dev"
Requires-Dist: packaging; extra == "dev"
Requires-Dist: cython>=3.0.10; extra == "dev"
Requires-Dist: numba>=0.55; extra == "dev"
Requires-Dist: matplotlib>=3; extra == "dev"
Requires-Dist: seaborn; extra == "dev"
Requires-Dist: pytest<9,>=8.4.1; extra == "dev"
Requires-Dist: pytest-randomly; extra == "dev"
Requires-Dist: pytest-xdist; extra == "dev"
Requires-Dist: pytest-cov; extra == "dev"
Requires-Dist: black[jupyter]~=25.9.0; extra == "dev"
Requires-Dist: isort~=6.0; extra == "dev"
Requires-Dist: colorama; extra == "dev"
Requires-Dist: flake8; extra == "dev"
Requires-Dist: flake8-bugbear; extra == "dev"
Requires-Dist: mypy>=1.3; extra == "dev"
Requires-Dist: ruff>=0.8.6; extra == "dev"
Requires-Dist: pyupgrade>=3.4.0; extra == "dev"
Requires-Dist: jupyterlab-code-formatter; extra == "dev"
Requires-Dist: jupyterlab>=4.4.8; extra == "dev"
Requires-Dist: zipp>=3.19.1; extra == "dev"
